MANIFEST.in
setup.cfg
setup.py
wekeypedia/__init__.py
wekeypedia/dataset.py
wekeypedia.egg-info/PKG-INFO
wekeypedia.egg-info/SOURCES.txt
wekeypedia.egg-info/dependency_links.txt
wekeypedia.egg-info/pbr.json
wekeypedia.egg-info/requires.txt
wekeypedia.egg-info/top_level.txt
wekeypedia/exporter/__init__.py
wekeypedia/exporter/mapping.py
wekeypedia/exporter/nx_json.py
wekeypedia/importer/__init__.py
wekeypedia/importer/neo4j.py
wekeypedia/importer/wkp_api.py
wekeypedia/metrics/__init__.py
wekeypedia/metrics/lsm.py
wekeypedia/metrics/tests/test_lsm.py
wekeypedia/parser/__init__.py
wekeypedia/parser/dataset.py
wekeypedia/parser/mediawiki.py
wekeypedia/wikipedia/__init__.py
wekeypedia/wikipedia/api.py
wekeypedia/wikipedia/page.py
wekeypedia/wikipedia/user.py